mlflow_extend/__init__.py
mlflow_extend/experiment.py
mlflow_extend/logging.py
mlflow_extend/mlflow.py
mlflow_extend/plotting.py
mlflow_extend/typing.py
mlflow_extend/utils.py
mlflow_extend/version.py
mlflow_extend/__pycache__/typing.cpython-36.pyc
mlflow_extend/testing/__init__.py
mlflow_extend/testing/utils.py
tests/__init__.py
tests/test_examples.py
tests/test_experiment.py
tests/test_init_exists.py
tests/test_logging.py
tests/test_plotting.py
tests/test_utils.py
tests/test_version.py
mlflow_extend-0.1.6.dist-info/LICENSE
mlflow_extend-0.1.6.dist-info/METADATA
mlflow_extend-0.1.6.dist-info/WHEEL
mlflow_extend-0.1.6.dist-info/top_level.txt
mlflow_extend-0.1.6.dist-info/RECORD
