Metadata-Version: 2.1
Name: mlflow-extend
Version: 0.1.6
Summary: Extend MLflow's functionality
Home-page: https://github.com/harupy/mlflow-extend
Maintainer: harupy
Maintainer-email: hkawamura0130@gmail.com
License: UNKNOWN
Project-URL: Documentation, https://mlflow-extend.readthedocs.io/en/latest/index.html
Project-URL: Source Code, https://github.com/harupy/mlflow-extend
Project-URL: Bug Tracker, https://github.com/harupy/mlflow-extend/issues
Platform: UNKNOWN
Classifier: License :: OSI Approved :: MIT License
Classifier: Programming Language :: Python :: 3.6
Classifier: Programming Language :: Python :: 3.7
Classifier: Programming Language :: Python :: 3.8
Requires-Python: >=3.6
Requires-Dist: pandas
Requires-Dist: pyarrow
Requires-Dist: numpy
Requires-Dist: matplotlib
Requires-Dist: seaborn
Requires-Dist: mlflow (>=1.7.0)
Requires-Dist: plotly
